jupytest.py
jupyter_pytest-0.1.5.dist-info/METADATA
jupyter_pytest-0.1.5.dist-info/WHEEL
jupyter_pytest-0.1.5.dist-info/top_level.txt
jupyter_pytest-0.1.5.dist-info/RECORD
