Metadata-Version: 2.1
Name: jupyter-pytest
Version: 0.1.5
Summary: UNKNOWN
Home-page: https://github.com/vahtras/jupyter-pytest
Author: Olav Vahtras
Author-email: olav.vahtras@gmail.com
License: UNKNOWN
Platform: UNKNOWN
Requires-Dist: jupyter
Requires-Dist: pytest
